[
  {
    "line": 1,
    "elements": [
      {
        "before": [
          {
            "result": {
              "duration": 795272339,
              "status": "passed"
            },
            "match": {
              "location": "Hooks.dbHook()"
            }
          },
          {
            "result": {
              "duration": 2318859349,
              "status": "passed"
            },
            "match": {
              "location": "Hooks.setUp()"
            }
          }
        ],
        "line": 25,
        "name": "my self",
        "description": "",
        "id": "information-about-me;my-self;;2",
        "after": [
          {
            "result": {
              "duration": 1349034,
              "status": "passed"
            },
            "match": {
              "location": "Hooks.afterDbHook()"
            }
          },
          {
            "result": {
              "duration": 92788650,
              "status": "passed"
            },
            "match": {
              "location": "Hooks.tearDown(Scenario)"
            }
          }
        ],
        "type": "scenario",
        "keyword": "Scenario Outline",
        "steps": [
          {
            "result": {
              "duration": 5677797353,
              "status": "passed"
            },
            "line": 19,
            "name": "user logs in using \"efewtrell8c@craigslist.org\"  \"jamesmay\"",
            "match": {
              "arguments": [
                {
                  "val": "\"efewtrell8c@craigslist.org\"",
                  "offset": 19
                },
                {
                  "val": "\"jamesmay\"",
                  "offset": 49
                }
              ],
              "location": "MyInfoStepDefs.user_logs_in_using(String,String)"
            },
            "keyword": "Given "
          },
          {
            "result": {
              "status": "undefined"
            },
            "line": 20,
            "name": "user is on the my self page",
            "match": {},
            "keyword": "When "
          },
          {
            "result": {
              "duration": 15343,
              "status": "skipped"
            },
            "line": 21,
            "name": "team info should match with the database records \"efewtrell8c@craigslist.org\"",
            "match": {
              "arguments": [
                {
                  "val": "\"efewtrell8c@craigslist.org\"",
                  "offset": 49
                }
              ],
              "location": "MyInfoStepDefs.team_info_should_match_with_the_database_records(String)"
            },
            "keyword": "Then "
          }
        ],
        "tags": [
          {
            "name": "@temp"
          },
          {
            "name": "@db"
          }
        ]
      },
      {
        "before": [
          {
            "result": {
              "duration": 425564282,
              "status": "passed"
            },
            "match": {
              "location": "Hooks.dbHook()"
            }
          },
          {
            "result": {
              "duration": 1143767537,
              "status": "passed"
            },
            "match": {
              "location": "Hooks.setUp()"
            }
          }
        ],
        "line": 26,
        "name": "my self",
        "description": "",
        "id": "information-about-me;my-self;;3",
        "after": [
          {
            "result": {
              "duration": 598266,
              "status": "passed"
            },
            "match": {
              "location": "Hooks.afterDbHook()"
            }
          },
          {
            "result": {
              "duration": 107445844,
              "status": "passed"
            },
            "match": {
              "location": "Hooks.tearDown(Scenario)"
            }
          }
        ],
        "type": "scenario",
        "keyword": "Scenario Outline",
        "steps": [
          {
            "result": {
              "duration": 5229801123,
              "status": "passed"
            },
            "line": 19,
            "name": "user logs in using \"jrowesby8h@google.co.uk\"  \"aldridgegrimsdith\"",
            "match": {
              "arguments": [
                {
                  "val": "\"jrowesby8h@google.co.uk\"",
                  "offset": 19
                },
                {
                  "val": "\"aldridgegrimsdith\"",
                  "offset": 46
                }
              ],
              "location": "MyInfoStepDefs.user_logs_in_using(String,String)"
            },
            "keyword": "Given "
          },
          {
            "result": {
              "status": "undefined"
            },
            "line": 20,
            "name": "user is on the my self page",
            "match": {},
            "keyword": "When "
          },
          {
            "result": {
              "duration": 9170,
              "status": "skipped"
            },
            "line": 21,
            "name": "team info should match with the database records \"jrowesby8h@google.co.uk\"",
            "match": {
              "arguments": [
                {
                  "val": "\"jrowesby8h@google.co.uk\"",
                  "offset": 49
                }
              ],
              "location": "MyInfoStepDefs.team_info_should_match_with_the_database_records(String)"
            },
            "keyword": "Then "
          }
        ],
        "tags": [
          {
            "name": "@temp"
          },
          {
            "name": "@db"
          }
        ]
      },
      {
        "before": [
          {
            "result": {
              "duration": 417695067,
              "status": "passed"
            },
            "match": {
              "location": "Hooks.dbHook()"
            }
          },
          {
            "result": {
              "duration": 1151095830,
              "status": "passed"
            },
            "match": {
              "location": "Hooks.setUp()"
            }
          }
        ],
        "line": 27,
        "name": "my self",
        "description": "",
        "id": "information-about-me;my-self;;4",
        "after": [
          {
            "result": {
              "duration": 568676,
              "status": "passed"
            },
            "match": {
              "location": "Hooks.afterDbHook()"
            }
          },
          {
            "result": {
              "duration": 91280388,
              "status": "passed"
            },
            "match": {
              "location": "Hooks.tearDown(Scenario)"
            }
          }
        ],
        "type": "scenario",
        "keyword": "Scenario Outline",
        "steps": [
          {
            "result": {
              "duration": 4537615881,
              "status": "passed"
            },
            "line": 19,
            "name": "user logs in using \"bmurkus8q@psu.edu\"  \"alicasanbroke\"",
            "match": {
              "arguments": [
                {
                  "val": "\"bmurkus8q@psu.edu\"",
                  "offset": 19
                },
                {
                  "val": "\"alicasanbroke\"",
                  "offset": 40
                }
              ],
              "location": "MyInfoStepDefs.user_logs_in_using(String,String)"
            },
            "keyword": "Given "
          },
          {
            "result": {
              "status": "undefined"
            },
            "line": 20,
            "name": "user is on the my self page",
            "match": {},
            "keyword": "When "
          },
          {
            "result": {
              "duration": 8277,
              "status": "skipped"
            },
            "line": 21,
            "name": "team info should match with the database records \"bmurkus8q@psu.edu\"",
            "match": {
              "arguments": [
                {
                  "val": "\"bmurkus8q@psu.edu\"",
                  "offset": 49
                }
              ],
              "location": "MyInfoStepDefs.team_info_should_match_with_the_database_records(String)"
            },
            "keyword": "Then "
          }
        ],
        "tags": [
          {
            "name": "@temp"
          },
          {
            "name": "@db"
          }
        ]
      }
    ],
    "name": "Information about me",
    "description": "",
    "id": "information-about-me",
    "keyword": "Feature",
    "uri": "src/test/resources/features/my_info.feature",
    "tags": []
  }
]